{"code":200,"current_page":171,"data":[{"id":1712,"url":"http://cdn.panghai.top/bing/2014/OHR.SheepKingPenguin_ZH-CN12005585545_1366x768.jpg","datetime":"2014-03-20"},{"id":1713,"url":"http://cdn.panghai.top/bing/2014/OHR.SpringFlowers_ZH-CN12146467355_1366x768.jpg","datetime":"2014-03-21"},{"id":1714,"url":"http://cdn.panghai.top/bing/2014/OHR.Dettifoss_ZH-CN7997622167_1366x768.jpg","datetime":"2014-03-22"},{"id":1715,"url":"http://cdn.panghai.top/bing/2014/OHR.WindMap_ZH-CN9036610001_1366x768.jpg","datetime":"2014-03-23"},{"id":1716,"url":"http://cdn.panghai.top/bing/2014/OHR.EarthStrongholds_ZH-CN10396925597_1366x768.jpg","datetime":"2014-03-24"},{"id":1717,"url":"http://cdn.panghai.top/bing/2014/OHR.AmauFerns_ZH-CN12037112009_1366x768.jpg","datetime":"2014-03-25"},{"id":1718,"url":"http://cdn.panghai.top/bing/2014/OHR.OrphanBabies_ZH-CN11125858807_1366x768.jpg","datetime":"2014-03-26"},{"id":1719,"url":"http://cdn.panghai.top/bing/2014/OHR.CancunPano_ZH-CN5697138969_1366x768.jpg","datetime":"2014-03-27"},{"id":1720,"url":"http://cdn.panghai.top/bing/2014/OHR.BadalingGreatWall_ZH-CN8953349136_1366x768.jpg","datetime":"2014-03-28"},{"id":1721,"url":"http://cdn.panghai.top/bing/2014/OHR.BanonProvence_ZH-CN11707348579_1366x768.jpg","datetime":"2014-03-29"}]}