{"code":200,"current_page":366,"data":[{"id":3663,"url":"https://cn.bing.com/th?id=OHR.CathedralMountBuffalo_ZH-CN4341947983_1920x1080.jpg&rf=LaDigue_1920x1080.jpg&pid=hp","datetime":"2019-07-25"},{"id":3664,"url":"https://cn.bing.com/th?id=OHR.ElkFallsBridge_ZH-CN3921681387_1920x1080.jpg&rf=LaDigue_1920x1080.jpg&pid=hp","datetime":"2019-07-26"},{"id":3665,"url":"https://cn.bing.com/th?id=OHR.CahuitaNP_ZH-CN3985565209_1920x1080.jpg&rf=LaDigue_1920x1080.jpg&pid=hp","datetime":"2019-07-27"},{"id":3666,"url":"https://cn.bing.com/th?id=OHR.PuffinSkomer_ZH-CN4039641381_1920x1080.jpg&rf=LaDigue_1920x1080.jpg&pid=hp","datetime":"2019-07-28"},{"id":3667,"url":"https://cn.bing.com/th?id=OHR.TrilliumLake_ZH-CN4079462365_1920x1080.jpg&rf=LaDigue_1920x1080.jpg&pid=hp","datetime":"2019-07-29"},{"id":3668,"url":"https://cn.bing.com/th?id=OHR.TortoiseMigration_ZH-CN4128473636_1920x1080.jpg&rf=LaDigue_1920x1080.jpg&pid=hp","datetime":"2019-07-30"},{"id":3669,"url":"https://cn.bing.com/th?id=OHR.TreeTower_ZH-CN4181961177_1920x1080.jpg&rf=LaDigue_1920x1080.jpg&pid=hp","datetime":"2019-07-31"},{"id":3670,"url":"https://cn.bing.com/th?id=OHR.LavaFlows_ZH-CN4235925500_1920x1080.jpg&rf=LaDigue_1920x1080.jpg&pid=hp","datetime":"2019-08-01"},{"id":3671,"url":"https://cn.bing.com/th?id=OHR.CrummockWater_ZH-CN9317792500_1920x1080.jpg&rf=LaDigue_1920x1080.jpg&pid=hp","datetime":"2019-08-02"},{"id":3672,"url":"https://cn.bing.com/th?id=OHR.UhuRLP_ZH-CN5421658032_1920x1080.jpg&rf=LaDigue_1920x1080.jpg&pid=hp","datetime":"2019-08-03"}]}