{"code":200,"current_page":47,"data":[{"id":465,"url":"http://cdn.panghai.top/bing/2010/OHR.IceBreaker_ZH-CN253810056_958x512.jpg","datetime":"2010-10-20"},{"id":466,"url":"http://cdn.panghai.top/bing/2010/OHR.SanJuanMountains_ZH-CN2583344187_958x512.jpg","datetime":"2010-10-21"},{"id":467,"url":"http://cdn.panghai.top/bing/2010/OHR.TrinityCollege_ZH-CN2407740162_958x512.jpg","datetime":"2010-10-22"},{"id":468,"url":"http://cdn.panghai.top/bing/2010/OHR.Odashirogahara_ZH-CN1266808518_958x512.jpg","datetime":"2010-10-23"},{"id":469,"url":"http://cdn.panghai.top/bing/2010/OHR.Pipefish_ZH-CN580919433_958x512.jpg","datetime":"2010-10-24"},{"id":470,"url":"http://cdn.panghai.top/bing/2010/OHR.BarossaValley_ZH-CN747125344_958x512.jpg","datetime":"2010-10-25"},{"id":471,"url":"http://cdn.panghai.top/bing/2010/OHR.Dongzu_ZH-CN1026091856_958x512.jpg","datetime":"2010-10-26"},{"id":472,"url":"http://cdn.panghai.top/bing/2010/OHR.TreeCamping_ZH-CN702991308_958x512.jpg","datetime":"2010-10-27"},{"id":473,"url":"http://cdn.panghai.top/bing/2010/OHR.SpermWhale_ZH-CN3039749287_958x512.jpg","datetime":"2010-10-28"},{"id":474,"url":"http://cdn.panghai.top/bing/2010/OHR.StMarksSquare_ZH-CN761640507_958x512.jpg","datetime":"2010-10-29"}]}