{"code":200,"current_page":7,"data":[{"id":61,"url":"http://cdn.panghai.top/bing/2009/OHR.MilfordSound_ZH-CN309284735_958x512.jpg","datetime":"2009-09-11"},{"id":62,"url":"http://cdn.panghai.top/bing/2009/OHR.RiverDouro_ZH-CN777308881_958x512.jpg","datetime":"2009-09-12"},{"id":63,"url":"http://cdn.panghai.top/bing/2009/OHR.Hippo_ZH-CN2503943788_958x512.jpg","datetime":"2009-09-13"},{"id":64,"url":"http://cdn.panghai.top/bing/2009/OHR.TibetDesert_ZH-CN52609807_958x512.jpg","datetime":"2009-09-14"},{"id":65,"url":"http://cdn.panghai.top/bing/2009/OHR.Forest_ZH-CN3033052193_958x512.jpg","datetime":"2009-09-15"},{"id":66,"url":"http://cdn.panghai.top/bing/2009/OHR.TrafficJam_ZH-CN174897961_958x512.jpg","datetime":"2009-09-16"},{"id":67,"url":"http://cdn.panghai.top/bing/2009/OHR.Subway_ZH-CN2033438546_958x512.jpg","datetime":"2009-09-17"},{"id":68,"url":"http://cdn.panghai.top/bing/2009/OHR.Lavender_ZH-CN3240965000_958x512.jpg","datetime":"2009-09-18"},{"id":69,"url":"http://cdn.panghai.top/bing/2009/OHR.SpiceMarket_ZH-CN2573271226_958x512.jpg","datetime":"2009-09-19"},{"id":70,"url":"http://cdn.panghai.top/bing/2009/OHR.CoyoteButte_ZH-CN200281706_958x512.jpg","datetime":"2009-09-20"}]}