{"code":200,"current_page":86,"data":[{"id":856,"url":"http://cdn.panghai.top/bing/2011/OHR.LaFortaleza_ZH-CN472301146_958x512.jpg","datetime":"2011-11-15"},{"id":857,"url":"http://cdn.panghai.top/bing/2011/OHR.LuangPuTuad_ZH-CN1878506117_958x512.jpg","datetime":"2011-11-16"},{"id":858,"url":"http://cdn.panghai.top/bing/2011/OHR.RingTailedLemur_ZH-CN1285084450_958x512.jpg","datetime":"2011-11-17"},{"id":859,"url":"http://cdn.panghai.top/bing/2011/OHR.RigaLatvia_ZH-CN2135823633_958x512.jpg","datetime":"2011-11-18"},{"id":860,"url":"http://cdn.panghai.top/bing/2011/OHR.KoreanLake_ZH-CN1390542987_958x512.jpg","datetime":"2011-11-19"},{"id":861,"url":"http://cdn.panghai.top/bing/2011/OHR.OrcinusOrca_ZH-CN293704572_958x512.jpg","datetime":"2011-11-20"},{"id":862,"url":"http://cdn.panghai.top/bing/2011/OHR.CurlyKale_ZH-CN532173873_958x512.jpg","datetime":"2011-11-21"},{"id":863,"url":"http://cdn.panghai.top/bing/2011/OHR.RedstoneColorado_ZH-CN262692736_958x512.jpg","datetime":"2011-11-22"},{"id":864,"url":"http://cdn.panghai.top/bing/2011/OHR.TagongGrasslands_ZH-CN1996935019_958x512.jpg","datetime":"2011-11-23"},{"id":865,"url":"http://cdn.panghai.top/bing/2011/OHR.Cranberries_ZH-CN21356066_958x512.jpg","datetime":"2011-11-24"}]}